MANIFEST.in
README.md
requirements.txt
setup.py
tests-requirements.txt
defcon/__init__.py
defcon/settings.py
defcon/tests_settings.py
defcon/urls.py
defcon/wsgi.py
defcon/plugins/__init__.py
defcon/plugins/alertmanager.py
defcon/plugins/base.py
defcon/plugins/endpoint.py
defcon/plugins/failing.py
defcon/plugins/jira.py
defcon/plugins/static.py
defcon/plugins/test_alertmanager.py
defcon/plugins/test_base.py
defcon/plugins/test_endpoint.py
defcon/plugins/test_failing.py
defcon/plugins/test_jira.py
defcon/plugins/test_static.py
defcon/status/__init__.py
defcon/status/admin.py
defcon/status/metrics.py
defcon/status/models.py
defcon/status/serializers.py
defcon/status/tests.py
defcon/status/urls.py
defcon/status/views.py
defcon/status/management/__init__.py
defcon/status/management/commands/__init__.py
defcon/status/management/commands/loadcomponents.py
defcon/status/management/commands/loadplugins.py
defcon/status/management/commands/runplugins.py
defcon/status/migrations/0001_initial.py
defcon/status/migrations/0002_auto_20171022_1858.py
defcon/status/migrations/0003_auto_20180223_1321.py
defcon/status/migrations/0004_auto_20180409_1040.py
defcon/status/migrations/__init__.py
defcon/status/static/favicon.ico
defcon/status/static/css/style.css
defcon/status/templates/badge.svg
defcon/status/templates/base.html
defcon/status/templates/bootstrap.html
defcon/status/templates/index.html
defcon/status/templates/status.html
defcon/status/templatetags/__init__.py
defcon/status/templatetags/defcon.py
defcon_monitoring.egg-info/PKG-INFO
defcon_monitoring.egg-info/SOURCES.txt
defcon_monitoring.egg-info/dependency_links.txt
defcon_monitoring.egg-info/requires.txt
defcon_monitoring.egg-info/top_level.txt